LICENSE
MANIFEST.in
README.md
setup.py
message_media_webhooks/__init__.py
message_media_webhooks/api_helper.py
message_media_webhooks/configuration.py
message_media_webhooks/decorators.py
message_media_webhooks/message_media_webhooks_client.py
message_media_webhooks/controllers/__init__.py
message_media_webhooks/controllers/base_controller.py
message_media_webhooks/controllers/webhooks_controller.py
message_media_webhooks/exceptions/__init__.py
message_media_webhooks/exceptions/api_exception.py
message_media_webhooks/exceptions/create_webhook_400_response_exception.py
message_media_webhooks/exceptions/retrieve_webhook_400_response_exception.py
message_media_webhooks/exceptions/update_webhook_400_response_exception.py
message_media_webhooks/http/__init__.py
message_media_webhooks/http/http_call_back.py
message_media_webhooks/http/http_client.py
message_media_webhooks/http/http_context.py
message_media_webhooks/http/http_method_enum.py
message_media_webhooks/http/http_request.py
message_media_webhooks/http/http_response.py
message_media_webhooks/http/requests_client.py
message_media_webhooks/http/auth/__init__.py
message_media_webhooks/http/auth/basic_auth.py
message_media_webhooks/models/__init__.py
message_media_webhooks/models/create_webhook_request.py
message_media_webhooks/models/update_webhook_request.py
messagemedia_webhooks_sdk.egg-info/PKG-INFO
messagemedia_webhooks_sdk.egg-info/SOURCES.txt
messagemedia_webhooks_sdk.egg-info/dependency_links.txt
messagemedia_webhooks_sdk.egg-info/requires.txt
messagemedia_webhooks_sdk.egg-info/top_level.txt
tests/__init__.py
tests/http_response_catcher.py
tests/test_helper.py
tests/controllers/__init__.py
tests/controllers/controller_test_base.py
tests/controllers/test_webhooks_controller.py