Metadata-Version: 1.1
Name: messagemedia-webhooks-sdk
Version: 1.0.0
Summary: The MessageMedia Webhooks allows you to subscribe to one or several events and when one of those events is triggered, an HTTP request is sent to the URL of your choice along with the message or payload. In simpler terms, it allows applications to "speak" to one another and get notified automatically when something new happens.
Home-page: https://developers.messagemedia.com
Author: MessageMedia Developers
Author-email: developers@messagemedia.com
License: Apache-2.0
Download-URL: https://github.com/messagemedia/messages-python-sdk
Platform: UNKNOWN
